<annotation>
	<folder>basic_dataset</folder>
	<filename>img270.png</filename>
	<path>C:\Users\Norbert\Desktop\nrbi\faculta\sem2\image_recognition_si\basic_dataset\img270.png</path>
	<source>
		<database>Unknown</database>
	</source>
	<size>
		<width>390</width>
		<height>275</height>
		<depth>3</depth>
	</size>
	<segmented>0</segmented>
	<object>
		<name>cedeaza</name>
		<pose>Unspecified</pose>
		<truncated>0</truncated>
		<difficult>0</difficult>
		<bndbox>
			<xmin>102</xmin>
			<ymin>86</ymin>
			<xmax>285</xmax>
			<ymax>265</ymax>
		</bndbox>
	</object>
</annotation>
