<annotation>
	<folder>basic_dataset</folder>
	<filename>img281.png</filename>
	<path>C:\Users\Norbert\Desktop\nrbi\faculta\sem2\image_recognition_si\basic_dataset\img281.png</path>
	<source>
		<database>Unknown</database>
	</source>
	<size>
		<width>242</width>
		<height>227</height>
		<depth>3</depth>
	</size>
	<segmented>0</segmented>
	<object>
		<name>cedeaza</name>
		<pose>Unspecified</pose>
		<truncated>0</truncated>
		<difficult>0</difficult>
		<bndbox>
			<xmin>50</xmin>
			<ymin>28</ymin>
			<xmax>184</xmax>
			<ymax>151</ymax>
		</bndbox>
	</object>
</annotation>
